genre_expand/__init__.py
genre_expand/genre_expand.py
genre_expand-0.0.4.dist-info/DESCRIPTION.rst
genre_expand-0.0.4.dist-info/METADATA
genre_expand-0.0.4.dist-info/RECORD
genre_expand-0.0.4.dist-info/WHEEL
genre_expand-0.0.4.dist-info/entry_points.txt
genre_expand-0.0.4.dist-info/metadata.json
genre_expand-0.0.4.dist-info/top_level.txt
