Metadata-Version: 2.0
Name: genre-expand
Version: 0.0.4
Summary: expand ID3 genre metadata
Home-page: https://github.com/huntrar/genre-expand
Author: Hunter Hammond
Author-email: huntrar@gmail.com
License: MIT
Keywords: expand id3 mp3 genre metadata wikipedia eyed3 music tag
Platform: UNKNOWN
Classifier: Development Status :: 4 - Beta
Classifier: Environment :: Console
Classifier: Intended Audience :: End Users/Desktop
Classifier: License :: OSI Approved :: MIT License
Classifier: Operating System :: OS Independent
Classifier: Programming Language :: Python :: 2
Classifier: Programming Language :: Python :: 2.6
Classifier: Programming Language :: Python :: 2.7
Classifier: Topic :: Utilities
Requires-Dist: eyed3
Requires-Dist: six
Requires-Dist: wikipedia
